Metadata-Version: 2.1
Name: upsonic-update
Version: 0.4.6
Summary: The cloud updating system for your python applications !
Home-page: https://github.com/Upsonic/Upsonic-Update
License: MIT
Platform: UNKNOWN
Requires-Python: >= 3
